[
  {
    "id": 1,
    "title": "Search and Discovery",
    "img": "https://www.material-tailwind.com/image/blog-11.jpeg",
    "desc": "Website visitors today demand a frictionless user experience — especially when using search.",
    "content": "This is the full content of the blog post on Search and Discovery."
  },
  {
    "id": 2,
    "title": "Last Visits in US",
    "img": "https://www.material-tailwind.com/image/blog-10.jpeg",
    "desc": "Wealth creation is an evolutionarily recent positive-sum game.",
    "content": "This is the full content of the blog post about Last Visits in US."
  }
]
